{
  "url": "https://agilestory.blog/3844631",
  "title": "P-Camp 후기",
  "date": "2007년 10월 11일",
  "author": "",
  "tags": [
    "src:ac2",
    "kind:content",
    "use:execution",
    "dom:general",
    "method:tdd",
    "scope:general",
    "evidence:field-case",
    "evidence:talk",
    "kw:tdd",
    "ac2",
    "ac2-content",
    "content",
    "event",
    "tdd",
    "testing"
  ],
  "extracted_at": "2026-03-02T23:11:57.739095",
  "post_id": "3844631",
  "raw_file": "3844631.html",
  "extraction_status": "success",
  "text_length": 1689,
  "cleaned_file": "3844631.md",
  "recovery_method": "trafilatura",
  "recovered": true,
  "recovered_at": "2026-03-02T23:36:37.299122",
  "tag_source": "ac2_taxonomy_v3_tuned_tl",
  "tags_updated_at": "2026-03-03T07:28:04.310Z"
}