{
  "url": "https://agilestory.blog/5348187",
  "title": "창의성의 아이러니",
  "date": "2010년 6월 30일",
  "author": "",
  "tags": [
    "src:ac2",
    "kind:content",
    "use:execution",
    "dom:general",
    "scope:general",
    "ac2",
    "ac2-content",
    "content"
  ],
  "extracted_at": "2026-03-02T23:18:31.006523",
  "post_id": "5348187",
  "raw_file": "5348187.html",
  "extraction_status": "empty",
  "recovery_method": "trafilatura",
  "text_length": 294,
  "recovered": true,
  "cleaned_file": "5348187.md",
  "recovered_at": "2026-03-02T23:36:38.434634",
  "tag_source": "ac2_taxonomy_v3_tuned_tl",
  "tags_updated_at": "2026-03-03T07:28:04.310Z"
}